multivec/__init__.py
multivec/data/__init__.py
multivec/data/load/__init__.py
multivec/data/load/csv.py
multivec/data/load/html.py
multivec/data/load/json.py
multivec/data/load/pdf.py
multivec/eval/__init__.py
multivec/exceptions.py
multivec/providers/__init__.py
multivec/providers/auth.py
multivec/providers/base.py
multivec/providers/cloud/__init__.py
multivec/providers/cloud/aws.py
multivec/providers/cloud/azure.py
multivec/providers/embedding.py
multivec/providers/llm/__init__.py
multivec/providers/llm/anthropic.py
multivec/providers/llm/bedrock.py
multivec/providers/llm/groq.py
multivec/providers/llm/ollama.py
multivec/providers/llm/openai.py
multivec/providers/vector_db/__init__.py
multivec/providers/vector_db/pinecone.py
multivec/providers/vector_db/qdrant.py
multivec/tool/__init__.py
multivec/tool/base_format.py
multivec/tool/crewai/__init__.py
multivec/tool/langchain/__init__.py
multivec/tool/langchain/pinecone.py
multivec/tool/langchain/qdrant.py
multivec/utils/__init__.py
multivec/utils/base_format.py
multivec-0.1.1.dist-info/LICENSE
multivec-0.1.1.dist-info/METADATA
multivec-0.1.1.dist-info/WHEEL
multivec-0.1.1.dist-info/RECORD
