Metadata-Version: 2.1
Name: multivec
Version: 0.1.1
Summary: Supercharge your LLMs with synthetic high-quality multimodal Data
License: Apache-2.0
Author: mr-green1337
Author-email: islam.hachimi2003@gmail.com
Requires-Python: >=3.12,<4.0
Classifier: License :: OSI Approved :: Apache Software License
Classifier: Programming Language :: Python :: 3
Classifier: Programming Language :: Python :: 3.12
Classifier: Programming Language :: Python :: 3.13
Requires-Dist: azure-storage-blob (>=12.23.1,<13.0.0)
Requires-Dist: boto3 (>=1.35.29,<2.0.0)
Requires-Dist: bs4 (>=0.0.2,<0.0.3)
Requires-Dist: cryptography (>=43.0.1,<44.0.0)
Requires-Dist: groq (>=0.11.0,<0.12.0)
Requires-Dist: ipykernel (>=6.29.5,<7.0.0)
Requires-Dist: matplotlib (>=3.9.2,<4.0.0)
Requires-Dist: numpy (>=2.0.0,<3.0.0)
Requires-Dist: openai (>=1.50.2,<2.0.0)
Requires-Dist: openai-clip (>=1.0.1,<2.0.0)
Requires-Dist: opencv-python (>=4.10.0.84,<5.0.0.0)
Requires-Dist: pandas (>=2.2.3,<3.0.0)
Requires-Dist: pillow (>=10.4.0,<11.0.0)
Requires-Dist: pinecone (>=5.3.1,<6.0.0)
Requires-Dist: pydantic (>=2.9.2,<3.0.0)
Requires-Dist: pymupdf (>=1.24.10,<2.0.0)
Requires-Dist: pytesseract (>=0.3.13,<0.4.0)
Requires-Dist: pytest (>=8.3.3,<9.0.0)
Requires-Dist: python-docx (>=1.1.2,<2.0.0)
Requires-Dist: qdrant-client (>=1.11.3,<2.0.0)
Requires-Dist: ruff (>=0.6.8,<0.7.0)
Requires-Dist: selenium (>=4.25.0,<5.0.0)
Requires-Dist: tenacity (>=9.0.0,<10.0.0)
